easysnowdata/__init__.py
easysnowdata/automatic_weather_stations.py
easysnowdata/easysnowdata.py
easysnowdata/hydroclimatology.py
easysnowdata/remote_sensing.py
easysnowdata/topography.py
easysnowdata/utils.py
easysnowdata-0.0.22.dist-info/licenses/LICENSE
easysnowdata-0.0.22.dist-info/METADATA
easysnowdata-0.0.22.dist-info/WHEEL
easysnowdata-0.0.22.dist-info/top_level.txt
easysnowdata-0.0.22.dist-info/RECORD
