Metadata-Version: 2.4
Name: easysnowdata
Version: 0.0.22
Summary: package to easily get data relevant to snow
Author-email: Eric Gagliano <egagli@uw.edu>
License: MIT License
Project-URL: Homepage, https://github.com/egagli/easysnowdata
Keywords: easysnowdata
Classifier: Intended Audience :: Developers
Classifier: License :: OSI Approved :: MIT License
Classifier: Natural Language :: English
Classifier: Programming Language :: Python :: 3.10
Classifier: Programming Language :: Python :: 3.11
Classifier: Programming Language :: Python :: 3.12
Classifier: Programming Language :: Python :: 3.13
Requires-Python: >=3.10
License-File: LICENSE
Requires-Dist: numpy
Requires-Dist: matplotlib
Requires-Dist: pandas
Requires-Dist: geopandas
Requires-Dist: rasterio
Requires-Dist: xarray
Requires-Dist: rioxarray
Requires-Dist: shapely
Requires-Dist: pystac-client
Requires-Dist: planetary-computer
Requires-Dist: odc-stac
Requires-Dist: earthengine-api
Requires-Dist: xee
Requires-Dist: beautifulsoup4
Requires-Dist: py3dep
Requires-Dist: earthaccess
Requires-Dist: contextily
Requires-Dist: folium
Requires-Dist: mapclassify
Requires-Dist: lxml
Requires-Dist: pytkdocs[numpy-style]
Requires-Dist: scikit-image
Requires-Dist: pytest
Provides-Extra: all
Requires-Dist: easysnowdata[extra]; extra == "all"
Provides-Extra: extra
Requires-Dist: pandas; extra == "extra"
Dynamic: license-file
